MANIFEST.in
VERSION
setup.py
pryvate/__init__.py
pryvate/defaultconfig.py
pryvate/server.py
pryvate.egg-info/PKG-INFO
pryvate.egg-info/SOURCES.txt
pryvate.egg-info/dependency_links.txt
pryvate.egg-info/entry_points.txt
pryvate.egg-info/not-zip-safe
pryvate.egg-info/requires.txt
pryvate.egg-info/top_level.txt
pryvate/blueprints/__init__.py
pryvate/blueprints/packages/__init__.py
pryvate/blueprints/packages/packages.py
pryvate/blueprints/pypi/__init__.py
pryvate/blueprints/pypi/pypi.py
pryvate/blueprints/simple/__init__.py
pryvate/blueprints/simple/simple.py
pryvate/blueprints/simple/templates/simple.html
pryvate/blueprints/simple/templates/simple_package.html
pryvate/db/__init__.py
pryvate/db/pryvatesql.py
tests/__init__.py
tests/test_pryvate.py
tests/test_pryvatesql.py