Metadata-Version: 1.1
Name: pryvate
Version: 1.0.0
Summary: Private PyPi proxy and repository
Home-page: https://github.com/Dinoshauer/pryvate
Author: Kasper Jacobsen
Author-email: k@mackwerk.dk
License: UNKNOWN
Download-URL: https://pypi.python.org/pypi/pryvate
Platform: UNKNOWN
Classifier: Development Status :: 3 - Alpha
Classifier: Environment :: Web Environment
Classifier: Intended Audience :: Developers
Classifier: Intended Audience :: System Administrators
Classifier: License :: OSI Approved :: MIT License
Classifier: Operating System :: POSIX :: Linux
Classifier: Programming Language :: Python :: 2.7
Classifier: Programming Language :: Python :: 3.4
Classifier: Topic :: Internet :: Proxy Servers
Classifier: Topic :: Software Development :: Libraries :: Python Modules
